trollflow2/__init__.py
trollflow2/_version.py
trollflow2/cli.py
trollflow2/dict_tools.py
trollflow2/launcher.py
trollflow2/logging.py
trollflow2/satpy_launcher.py
trollflow2/plugins/__init__.py
trollflow2/plugins/s3.py
trollflow2/tests/__init__.py
trollflow2/tests/test_cli.py
trollflow2/tests/test_dict_tools.py
trollflow2/tests/test_launcher.py
trollflow2/tests/test_logging.py
trollflow2/tests/test_s3_plugins.py
trollflow2/tests/test_trollflow2.py
trollflow2/tests/utils.py
trollflow2-0.17.1.dist-info/METADATA
trollflow2-0.17.1.dist-info/WHEEL
trollflow2-0.17.1.dist-info/entry_points.txt
trollflow2-0.17.1.dist-info/licenses/LICENSE
trollflow2-0.17.1.dist-info/RECORD
